polarmints/__init__.py
polarmints/aws.py
polarmints/core.py
polarmints/dag/__init__.py
polarmints/dag/core.py
polarmints/dag/dagdf.py
polarmints/dateutils.py
polarmints/pandas.py
polarmints/pandas_mirror.py
polarmints/sugar.py
polarmints/utils.py
polarmints-0.1.25.dist-info/LICENSE
polarmints-0.1.25.dist-info/METADATA
polarmints-0.1.25.dist-info/WHEEL
polarmints-0.1.25.dist-info/RECORD
