Metadata-Version: 2.1
Name: polarmints
Version: 0.1.25
Summary: syntactic sugar and additional namespaces for polars
Author: John Smith
Requires-Python: >=3.7
Classifier: Programming Language :: Python :: 3
Classifier: Programming Language :: Python :: 3.7
Classifier: Programming Language :: Python :: 3.8
Classifier: Programming Language :: Python :: 3.9
Classifier: Programming Language :: Python :: 3.10
Classifier: Programming Language :: Python :: 3.11
Provides-Extra: aws
Provides-Extra: cal
Requires-Dist: networkx
Requires-Dist: polars
Requires-Dist: swarkn
